setup.py
dsnd_probability_08_2021/Binomialdistribution.py
dsnd_probability_08_2021/Gaussiandistribution.py
dsnd_probability_08_2021/Generaldistribution.py
dsnd_probability_08_2021/__init__.py
dsnd_probability_08_2021.egg-info/PKG-INFO
dsnd_probability_08_2021.egg-info/SOURCES.txt
dsnd_probability_08_2021.egg-info/dependency_links.txt
dsnd_probability_08_2021.egg-info/not-zip-safe
dsnd_probability_08_2021.egg-info/top_level.txt