Metadata-Version: 1.0
Name: dsnd-probability-08-2021
Version: 0.1
Summary: Gaussian and Binomial distributions | Udacity Nanodegree Execise
Home-page: UNKNOWN
Author: Andre Vargas
Author-email: UNKNOWN
License: UNKNOWN
Platform: UNKNOWN
